voiceio
